django_lightweight_tests/__init__.py
django_lightweight_tests/lightweight_test.py
django_lightweight_tests/tests.py
django_lightweight_tests-0.0.1.dist-info/LICENSE
django_lightweight_tests-0.0.1.dist-info/METADATA
django_lightweight_tests-0.0.1.dist-info/WHEEL
django_lightweight_tests-0.0.1.dist-info/top_level.txt
django_lightweight_tests-0.0.1.dist-info/RECORD
