Metadata-Version: 2.1
Name: django-lightweight-tests
Version: 0.0.1
Summary: Run Django tests with optimization options to decrease runtime while keeping them trustable
Home-page: https://github.com/luisccf/django-lightweight-tests
Author: Luis Carlos Cardoso
Author-email: luisccf@me.com
License: UNKNOWN
Platform: UNKNOWN
Classifier: Programming Language :: Python :: 3
Classifier: License :: OSI Approved :: MIT License
Classifier: Operating System :: OS Independent
Requires-Python: >=3.6
